{"title": "7 Day & Map Room", "body": "\n\t\t\t\t\tBrowse local weather forecast images. Related: Sign up for daily weather forecast emails or severe weather alerts for your location.RadarSatelliteHigh TemperaturesLow TemperaturesU.S. TemperaturesDewpointFeels LikeFlood ThreatHeat AlertsThunderstorm/Tornado AlertsWinter Weather AlertsRelated: Sign up for daily weather forecast emails or severe weather alerts for your location. \n\t\t\t\t", "url": "https://www.wbaltv.com/article/map-room/4314744", "date": null, "access_date": "2021-05-07T19:54:18.580056"}